Verilog/Assignment/Tic tac toe/tic_tac_toe_game.v


module tic_tac_toe_game (
  input play, reset, clk, 
  input [3:0] xPlayerPos, oPlayerPos,
  output[1:0] gameWinner, pos1, pos2, pos3, pos4, pos5, pos6, pos7, pos8, pos9
  );
  
  parameter [1:0] IDLE=00, O_PLAYER=01, X_PLAYER=10, GAME_OVER=11;
  
  reg [1:0] currentState, nextState;
  reg [1:0] board[0:8];
  reg [3:0] moveCount;
  reg illegalMoveoPlayer, illegalMovexPlayer;
  reg noVacantSpace, result;
  reg [1:0] winner;
  integer i,j;
  
  assign gameWinner = winner;
  assign pos1=board[0];
  assign pos2=board[1];
  assign pos3=board[2];
  assign pos4=board[3];
  assign pos5=board[4];
  assign pos6=board[5];
  assign pos7=board[6];
  assign pos8=board[7];
  assign pos9=board[8];
  
  always @(*) begin
    illegalMoveoPlayer = (board[oPlayerPos-1] == 0) ? 0 : 1;
    illegalMovexPlayer = (board[xPlayerPos-1] == 0) ? 0 : 1;
  end
    
  
  
  always @(posedge reset or result or noVacantSpace ) begin
    if (result && winner==2'b01)begin
      $display("O_PLAYER WON THE GAME :)");#2;
    end
    else if (result && winner==2'b10) begin
      $display("X_PLAYER WON THE GAME :)");#2;
    end
    else if (noVacantSpace)
      $display("DRAW -_-");#2;
   
   
    noVacantSpace = 0;
    currentState = IDLE;
    moveCount = 0;
    for ( i = 0; i < 9; i = i + 1)
      board[i] = 0;
     winner=2'b00;
     result=0; 
  end
  
  always @(nextState) begin
   

    for ( i = 0; i <= 2; i = i + 1) begin
      for ( j = 0; j <= 2; j = j + 1) begin
        case (board[3*i+j])
          0: $write(". ");
          1: $write("O ");
          2: $write("X ");
          default: $write(". ");
        endcase
      end $display("");
    end $display("");
  end
  
  always @(posedge clk) begin
    currentState = nextState;
  end

  always @(negedge clk) begin
    case (currentState)
      IDLE: begin
        if (play && ~reset) begin
          nextState = O_PLAYER;
        end else begin
          nextState = currentState;
        end
      end

      O_PLAYER: begin
        $display("O Player's Move");
        
        if (~illegalMoveoPlayer) begin
          nextState = X_PLAYER;
          board[oPlayerPos-1] = 1;
          moveCount = moveCount + 1;
        end else if (noVacantSpace || result) begin
          nextState = GAME_OVER;
        end else if (illegalMoveoPlayer) begin
          nextState = currentState;
          $display("Invalid Move, Please try again");
        end else begin
          nextState = currentState;
        end
      end

      X_PLAYER: begin
        $display("X Plyaer's Move");
       
        if (~illegalMovexPlayer) begin
          nextState = O_PLAYER;
          board[xPlayerPos-1] = 2;
          moveCount = moveCount + 1;
        end else if (noVacantSpace || result) begin
          nextState = GAME_OVER;
        end else if (illegalMovexPlayer) begin
          nextState = currentState;
          $display("Invalid Move, Please try again");
        end else begin
          nextState = currentState;
        end
      end

      GAME_OVER: begin
        if (~reset) begin
          nextState = currentState;
        end else begin
          nextState = IDLE;
        end
      end
    endcase
  end
  
  always @(currentState) begin

    if (moveCount == 9)
      noVacantSpace = 1;
    else
      noVacantSpace = 0;
  end
  
  always @(currentState) begin
    if (board[0] == 1 && board[1] == 1 && board[2] == 1) begin
      result = 1;winner = 2'b01;
    end else if (board[0] == 1 && board[3] == 1 && board[6] == 1) begin
      result = 1;winner = 2'b01;
    end else if (board[0] == 1 && board[4] == 1 && board[8] == 1) begin
      result = 1;winner = 2'b01;
    end else if (board[1] == 1 && board[4] == 1 && board[7] == 1) begin
      result = 1;winner = 2'b01;
    end else if (board[2] == 1 && board[5] == 1 && board[8] == 1) begin
      result = 1;winner = 2'b01;
    end else if (board[3] == 1 && board[4] == 1 && board[5] == 1) begin
      result = 1;winner = 2'b01;
    end else if (board[6] == 1 && board[7] == 1 && board[8] == 1) begin
      result = 1;winner = 2'b01;
    end else if (board[2] == 1 && board[4] == 1 && board[6] == 1) begin
      result = 1;winner = 2'b01;
    end else if (board[0] == 2 && board[1] == 2 && board[2] == 2) begin
      result = 1;winner = 2'b10;
    end else if (board[0] == 2 && board[3] == 2 && board[6] == 2) begin
      result = 1;winner = 2'b10;
    end else if (board[0] == 2 && board[4] == 2 && board[8] == 2) begin
      result = 1;winner = 2'b10;
    end else if (board[1] == 2 && board[4] == 2 && board[7] == 2) begin
      result = 1;winner = 2'b10;
    end else if (board[2] == 2 && board[5] == 2 && board[8] == 2) begin
      result = 1;winner = 2'b10;
    end else if (board[3] == 2 && board[4] == 2 && board[5] == 2) begin
      result = 1;winner = 2'b10;
    end else if (board[6] == 2 && board[7] == 2 && board[8] == 2) begin
      result = 1;winner = 2'b10;
    end else if (board[2] == 2 && board[4] == 2 && board[6] == 2) begin
      result = 1;winner = 2'b10;
    end
     
  end
endmodule

Verilog/Assignment/Tic tac toe/tb.v
`timescale 1ns/1ns
`include "tic_tac_toe_game.v"
module tb;
  reg play, reset, clk=1;
  reg [3:0] xPlayerPos, oPlayerPos;
  wire[1:0] gameWinner,pos1, pos2, pos3, pos4, pos5, pos6, pos7, pos8, pos9;
  
  tic_tac_toe_game uut(
    play, reset, clk, 
    xPlayerPos, oPlayerPos, 
    gameWinner,pos1, pos2, pos3, pos4, pos5, pos6, pos7, pos8, pos9
  );
  always begin #5 clk = ~clk;
  end
  initial
    begin
       
    $dumpfile("tb.vcd");
    $dumpvars(0, tb);
  
      reset = 1;
      
      reset = 0;#10
      play = 1;#10;
      
      xPlayerPos = 5;#10;xPlayerPos=0;
      oPlayerPos = 1;#10;oPlayerPos=0;
      xPlayerPos = 5;#10;xPlayerPos=0;
      oPlayerPos = 3;#10;oPlayerPos=0;
      xPlayerPos = 2;#10;xPlayerPos=0;
      oPlayerPos = 6;#10;oPlayerPos=0;
      xPlayerPos = 8;#10;xPlayerPos=0;
     
      
      play=0;
      oPlayerPos = 5;#10#10#10;

      
      $finish;
    end 
endmodule

Verilog/Assignment/Tic tac toe/tb.vcd
$date
	Sun Jan 14 16:30:04 2024
$end
$version
	Icarus Verilog
$end
$timescale
	1ns
$end
$scope module tb $end
$var wire 2 ! pos9 [1:0] $end
$var wire 2 " pos8 [1:0] $end
$var wire 2 # pos7 [1:0] $end
$var wire 2 $ pos6 [1:0] $end
$var wire 2 % pos5 [1:0] $end
$var wire 2 & pos4 [1:0] $end
$var wire 2 ' pos3 [1:0] $end
$var wire 2 ( pos2 [1:0] $end
$var wire 2 ) pos1 [1:0] $end
$var wire 2 * gameWinner [1:0] $end
$var reg 1 + clk $end
$var reg 4 , oPlayerPos [3:0] $end
$var reg 1 - play $end
$var reg 1 . reset $end
$var reg 4 / xPlayerPos [3:0] $end
$scope module uut $end
$var wire 1 + clk $end
$var wire 2 0 gameWinner [1:0] $end
$var wire 4 1 oPlayerPos [3:0] $end
$var wire 1 - play $end
$var wire 2 2 pos1 [1:0] $end
$var wire 2 3 pos2 [1:0] $end
$var wire 2 4 pos3 [1:0] $end
$var wire 2 5 pos4 [1:0] $end
$var wire 2 6 pos5 [1:0] $end
$var wire 2 7 pos6 [1:0] $end
$var wire 2 8 pos7 [1:0] $end
$var wire 2 9 pos8 [1:0] $end
$var wire 2 : pos9 [1:0] $end
$var wire 1 . reset $end
$var wire 4 ; xPlayerPos [3:0] $end
$var parameter 2 < GAME_OVER $end
$var parameter 2 = IDLE $end
$var parameter 2 > O_PLAYER $end
$var parameter 2 ? X_PLAYER $end
$var reg 2 @ currentState [1:0] $end
$var reg 1 A illegalMoveoPlayer $end
$var reg 1 B illegalMovexPlayer $end
$var reg 4 C moveCount [3:0] $end
$var reg 2 D nextState [1:0] $end
$var reg 1 E noVacantSpace $end
$var reg 1 F result $end
$var reg 2 G winner [1:0] $end
$var integer 32 H i [31:0] $end
$var integer 32 I j [31:0] $end
$upscope $end
$upscope $end
$enddefinitions $end
$comment Show the parameter values. $end
$dumpall
b10 ?
b1 >
b0 =
b11 <
$end
#0
$dumpvars
bx I
bx H
bx G
xF
xE
bx D
bx C
xB
xA
bx @
bx ;
bx :
bx 9
bx 8
bx 7
bx 6
bx 5
bx 4
bx 3
bx 2
bx 1
bx 0
bx /
0.
x-
bx ,
1+
bx *
bx )
bx (
bx '
bx &
bx %
bx $
bx #
bx "
bx !
$end
#2
0F
b0 *
b0 0
b0 G
b0 !
b0 :
b0 "
b0 9
b0 #
b0 8
b0 $
b0 7
b0 %
b0 6
b0 &
b0 5
b0 '
b0 4
b0 (
b0 3
b0 )
b0 2
b1001 H
b0 C
b0 @
0E
#5
b11 I
b11 H
b0 D
0+
#10
1+
1-
#15
b11 I
b11 H
b1 D
0+
#20
b1 @
0B
1+
b101 /
b101 ;
0-
#25
0+
#30
xB
0A
1+
b1 ,
b1 1
b0 /
b0 ;
#35
1A
b11 I
b11 H
b1 C
b1 )
b1 2
b10 D
0+
#40
b10 @
0B
xA
1+
b101 /
b101 ;
b0 ,
b0 1
#45
1B
b11 I
b11 H
b10 C
b10 %
b10 6
b1 D
0+
#50
b1 @
xB
0A
1+
b11 ,
b11 1
b0 /
b0 ;
#55
1A
b11 I
b11 H
b11 C
b1 '
b1 4
b10 D
0+
#60
b10 @
0B
xA
1+
b10 /
b10 ;
b0 ,
b0 1
#65
1B
b11 I
b11 H
b100 C
b10 (
b10 3
b1 D
0+
#70
b1 @
xB
0A
1+
b110 ,
b110 1
b0 /
b0 ;
#75
1A
b11 I
b11 H
b101 C
b1 $
b1 7
b10 D
0+
#80
b10 @
0B
xA
1+
b1000 /
b1000 ;
b0 ,
b0 1
#85
1B
b11 I
b11 H
b110 C
b10 "
b10 9
b1 D
0+
#90
b10 *
b10 0
b10 G
1F
b1 @
xB
1A
1+
b101 ,
b101 1
b0 /
b0 ;
#94
0A
0F
b0 *
b0 0
b0 G
b0 "
b0 9
b0 $
b0 7
b0 %
b0 6
b0 '
b0 4
b0 (
b0 3
b0 )
b0 2
b1001 H
b0 C
b0 @
#95
b11 I
b11 H
b0 D
0+
