Verilog/Assignment/Tic tac toe/tictactoe_new.v
module tictactoe_new(
     clk,
     rst,
   
    row,
     column,
    enter,//for conforming input
     winner,
    pos1, pos2, pos3, pos4, pos5, pos6, pos7, pos8, pos9
);

    input clk;
    input rst;
  
    
    input  [1:0] row;
    input  [1:0] column;
    input  enter;//for conforming input
    output [1:0] winner;
    output [1:0] pos1, pos2, pos3, pos4, pos5, pos6, pos7, pos8, pos9;

// Parameter declarations
parameter X_PLAYER = 2'b01;
parameter O_PLAYER = 2'b10;
parameter EMPTY = 2'b00;

// Internal signals
reg [1:0] current_player;
reg [1:0]  po1, po2, po3, po4, po5, po6, po7, po8, po9;
reg [8:0] pos_occupancy;
reg [1:0] game_winner;
reg [2:0] move[1:0];
reg valid_move,check_winner;
integer k, j,i;
assign winner = game_winner;


assign pos1 = po1;
assign pos2 = po2;
assign pos3 = po3;

assign pos4 = po4;
assign pos5 = po5;
assign pos6 = po6;

assign pos7 = po7;
assign pos8 = po8;
assign pos9 = po9;

// Initializations
initial begin
    current_player = X_PLAYER;
    game_winner = EMPTY;
     pos_occupancy = 9'b000000000; // Initially all positions are empty
    po1 = EMPTY;
    po2 = EMPTY;
    po3 = EMPTY;
    po4 = EMPTY;
    po5 = EMPTY;
    po6 = EMPTY;
    po7 = EMPTY;
    po8 = EMPTY;
    po9 = EMPTY;
    move[0]=EMPTY;
    move[1]=EMPTY;
    valid_move=1;
end

// Game logic
always @(posedge clk or rst or enter) begin

    if (rst || game_winner==2'b01 || game_winner==2'b10 || pos_occupancy == 9'b111111111) begin
        current_player = X_PLAYER;
        game_winner = EMPTY;
        //  integer k=0, j=0;
    pos_occupancy = 9'b000000000; // Reset occupancy status
        // Reset individual position variables
        po1 = EMPTY;
        po2 = EMPTY;
        po3 = EMPTY;
        po4 = EMPTY;
        po5 = EMPTY;
        po6 = EMPTY;
        po7 = EMPTY;
        po8 = EMPTY;
        po9 = EMPTY;
        move[0]=EMPTY;
        move[1]=EMPTY;
    end 
    
    if(enter)begin
            if (current_player==X_PLAYER)
                $display("X_PLAYER'S MOVE:)");
            if(current_player==O_PLAYER)
                $display("O_PLAYER'S MOVE:)");
            
            $display("");



             move[0]=row;
             move[1]=column;

                if (move[0] < 3 && move[1] < 3 && (pos_occupancy[move[0]*3 + move[1]] == 0)) begin
                valid_move=1; // Valid move
                end
                else begin
                valid_move=0;// Invalid move
                end
 
            
        
        
        if (valid_move) begin
            pos_occupancy[move[0]*3 + move[1]] = 1;



            
             if (move[0] == 2'b00 && move[1] == 2'b00) begin
       po1 <= current_player;
end else if (move[0] == 2'b00 && move[1] == 2'b01) begin
    po2 = current_player;
end else if (move[0] == 2'b00 && move[1] == 2'b10) begin
    po3 = current_player;
end else if (move[0] == 2'b01 && move[1] == 2'b00) begin
    po4 = current_player;
end else if (move[0] == 2'b01 && move[1] == 2'b01) begin
    po5 = current_player;
end else if (move[0] == 2'b01 && move[1] == 2'b10) begin
    po6 = current_player;
end else if (move[0] == 2'b10 && move[1] == 2'b00) begin
    po7 = current_player;
end else if (move[0] == 2'b10 && move[1] == 2'b01) begin
    po8 = current_player;
end else if (move[0] == 2'b10 && move[1] == 2'b10) begin
    po9 = current_player;
end else begin
    // Invalid move, do nothing
end

        

     if ((po1 == current_player && po2 == current_player && po3 == current_player) ||
        (po4 == current_player && po5 == current_player && po6 == current_player) ||
        (po7 == current_player && po8 == current_player && po9 == current_player) ||
        (po1 == current_player && po4 == current_player && po7 == current_player) ||
        (po2 == current_player && po5 == current_player && po8 == current_player) ||
        (po3 == current_player && po6 == current_player && po9 == current_player) ||
        (po1 == current_player && po5 == current_player && po9 == current_player) ||
        (po3 == current_player && po5 == current_player && po7 == current_player)) begin
        check_winner = 1; // Winner found
    end
    else begin
        check_winner = 0;
    end

         if (check_winner) begin
                game_winner = current_player;
            end else begin
                // Switch player
                #1;
                current_player = (current_player == X_PLAYER) ? O_PLAYER : X_PLAYER;
            end

          // Display the Tic-Tac-Toe board
case (po1)
    0: $write(". ");
    1: $write("X ");
    2: $write("O ");
    default: $write(". ");
endcase

case (po2)
    0: $write(". ");
    1: $write("X ");
    2: $write("O ");
    default: $write(". ");
endcase

case (po3)
    0: $write(". ");
    1: $write("X ");
    2: $write("O ");
    default: $write(". ");
endcase
$display("");

case (po4)
    0: $write(". ");
    1: $write("X ");
    2: $write("O ");
    default: $write(". ");
endcase

case (po5)
    0: $write(". ");
    1: $write("X ");
    2: $write("O ");
    default: $write(". ");
endcase

case (po6)
    0: $write(". ");
    1: $write("X ");
    2: $write("O ");
    default: $write(". ");
endcase
$display("");

case (po7)
    0: $write(". ");
    1: $write("X ");
    2: $write("O ");
    default: $write(". ");
endcase

case (po8)
    0: $write(". ");
    1: $write("X ");
    2: $write("O ");
    default: $write(". ");
endcase

case (po9)
    0: $write(". ");
    1: $write("X ");
    2: $write("O ");
    default: $write(". ");
endcase
$display("");
$display("");

   
 if (game_winner==X_PLAYER)
      $display("X_PLAYER WON THE GAME :)");
 if(game_winner==O_PLAYER)
      $display("O_PLAYER WON THE GAME :)");
 if (check_winner == 0 && pos_occupancy == 9'b111111111)
      $display("DRAW -_-");




         end
    else begin
        $display("INVALID MOVE :(");
        $display("");
    end  

       
    end
end



endmodule

Verilog/Assignment/Tic tac toe/tictactoenew_tb.v
`timescale 1ns/1ns
`include "tictactoe_new.v"


module tictactoenew_tb;

    // Inputs
    reg clk=0;
    reg rst;
   
    reg [1:0] row;
    reg [1:0] column;
    reg enter=0;  // Trigger to confirm input

    // Outputs
    wire [1:0] winner;
    wire [1:0]  pos1, pos2, pos3, pos4, pos5, pos6, pos7, pos8, pos9;

    // Instantiate the tictactoenew module
    tictactoe_new uut (
        .clk(clk),
        .rst(rst),
        
        .row(row),
        .column(column),
        .enter(enter),
        .winner(winner),
        .pos1(pos1),
        .pos2(pos2),
        .pos3(pos3),
        .pos4(pos4),
        .pos5(pos5),
        .pos6(pos6),
        .pos7(pos7),
        .pos8(pos8),
        .pos9(pos9)
    );

    // Clock generation
    always  begin
        
    
        
       #5; clk = ~clk;
    end

    // Test sequence
    initial begin
        // Initialize inputs
        $dumpfile("tictactoenew_tb.vcd");
        $dumpvars(0,tictactoenew_tb);
        rst = 1;
         // X_PLAYER
        enter = 0;
        row = 2'b00;
        column = 2'b00;
        

        // Apply reset and wait for a few clock cycles
        #10 ;rst = 0;
        

        // Play some moves
        #30 ; row = 2'b00; column = 2'b10;#05; enter = 1;#5; enter = 0; // X_PLAYER, (row=1, col=3)
        #30; row = 2'b01; column = 2'b00;#5; enter = 1;#5; enter = 0;  // O_PLAYER, (row=2, col=1)
        #30 ; row = 2'b10; column = 2'b10;#5; enter = 1;#5; enter = 0;  // X_PLAYER, (row=3, col=3)
        #30 ; row = 2'b10; column = 2'b10;#5; enter = 1;#5; enter = 0;  // O_PLAYER, (row=3, col=3)//invalid
        #30 ; row = 2'b01; column = 2'b01;#5; enter = 1;#5; enter = 0; // O_PLAYER, (row=2, col=1)
        #30 ; row = 2'b01; column = 2'b10;#5; enter = 1;#5; enter = 0; // X_PLAYER, (row=2, col=1)
        
        // // Add more test scenarios as needed

        // End simulation after some time
        #20;$finish;
    end

    

endmodule

Verilog/Assignment/Tic tac toe/tictactoenew_tb.vcd
$date
	Sat Jan 06 18:25:23 2024
$end
$version
	Icarus Verilog
$end
$timescale
	1ns
$end
$scope module tictactoenew_tb $end
$var wire 2 ! winner [1:0] $end
$var wire 2 " pos9 [1:0] $end
$var wire 2 # pos8 [1:0] $end
$var wire 2 $ pos7 [1:0] $end
$var wire 2 % pos6 [1:0] $end
$var wire 2 & pos5 [1:0] $end
$var wire 2 ' pos4 [1:0] $end
$var wire 2 ( pos3 [1:0] $end
$var wire 2 ) pos2 [1:0] $end
$var wire 2 * pos1 [1:0] $end
$var reg 1 + clk $end
$var reg 2 , column [1:0] $end
$var reg 1 - enter $end
$var reg 2 . row [1:0] $end
$var reg 1 / rst $end
$scope module uut $end
$var wire 1 + clk $end
$var wire 2 0 column [1:0] $end
$var wire 1 - enter $end
$var wire 2 1 pos1 [1:0] $end
$var wire 2 2 pos2 [1:0] $end
$var wire 2 3 pos3 [1:0] $end
$var wire 2 4 pos4 [1:0] $end
$var wire 2 5 pos5 [1:0] $end
$var wire 2 6 pos6 [1:0] $end
$var wire 2 7 pos7 [1:0] $end
$var wire 2 8 pos8 [1:0] $end
$var wire 2 9 pos9 [1:0] $end
$var wire 2 : row [1:0] $end
$var wire 1 / rst $end
$var wire 2 ; winner [1:0] $end
$var parameter 2 < EMPTY $end
$var parameter 2 = O_PLAYER $end
$var parameter 2 > X_PLAYER $end
$var reg 1 ? check_winner $end
$var reg 2 @ current_player [1:0] $end
$var reg 2 A game_winner [1:0] $end
$var reg 2 B po1 [1:0] $end
$var reg 2 C po2 [1:0] $end
$var reg 2 D po3 [1:0] $end
$var reg 2 E po4 [1:0] $end
$var reg 2 F po5 [1:0] $end
$var reg 2 G po6 [1:0] $end
$var reg 2 H po7 [1:0] $end
$var reg 2 I po8 [1:0] $end
$var reg 2 J po9 [1:0] $end
$var reg 9 K pos_occupancy [8:0] $end
$var reg 1 L valid_move $end
$upscope $end
$upscope $end
$enddefinitions $end
$comment Show the parameter values. $end
$dumpall
b1 >
b10 =
b0 <
$end
#0
$dumpvars
1L
b0 K
b0 J
b0 I
b0 H
b0 G
b0 F
b0 E
b0 D
b0 C
b0 B
b0 A
b1 @
x?
b0 ;
b0 :
b0 9
b0 8
b0 7
b0 6
b0 5
b0 4
b0 3
b0 2
b0 1
b0 0
1/
b0 .
0-
b0 ,
0+
b0 *
b0 )
b0 (
b0 '
b0 &
b0 %
b0 $
b0 #
b0 "
b0 !
$end
#5
1+
#10
0+
0/
#15
1+
#20
0+
#25
1+
#30
0+
#35
1+
#40
0+
b10 ,
b10 0
#45
0?
b1 (
b1 3
b1 D
b100 K
1+
1-
#46
b10 @
#50
0+
0-
#55
1+
#60
0+
#65
1+
#70
0+
#75
1+
#80
0+
b0 ,
b0 0
b1 .
b1 :
#85
b10 '
b10 4
b10 E
b1100 K
1+
1-
#86
b1 @
#90
0+
0-
#95
1+
#100
0+
#105
1+
#110
0+
#115
1+
#120
0+
b10 ,
b10 0
b10 .
b10 :
#125
b1 "
b1 9
b1 J
b100001100 K
1+
1-
#126
b10 @
#130
0+
0-
#135
1+
#140
0+
#145
1+
#150
0+
#155
1+
#160
0+
#165
0L
1+
1-
#170
0+
0-
#175
1+
#180
0+
#185
1+
#190
0+
#195
1+
#200
0+
b1 ,
b1 0
b1 .
b1 :
#205
b10 &
b10 5
b10 F
b100011100 K
1L
1+
1-
#206
b1 @
#210
0+
0-
#215
1+
#220
0+
#225
1+
#230
0+
#235
1+
#240
0+
b10 ,
b10 0
#245
b1 !
b1 ;
b1 A
1?
b1 %
b1 6
b1 G
b100111100 K
1+
1-
#250
b0 "
b0 9
b0 J
b0 %
b0 6
b0 G
b0 &
b0 5
b0 F
b0 '
b0 4
b0 E
b0 (
b0 3
b0 D
b0 K
b0 !
b0 ;
b0 A
0+
0-
