Verilog/Assignment/assg-3/decimal_counter/bcdcounter.v
module bcdcounter(clk,o,en);
input clk;
output[15:0] o;
output en;
reg[3:0] a=0,b=0,c=0,d=0;
assign {o[3:0],o[7:4],o[11:8],o[15:12]}={a,b,c,d};
always @(posedge clk ) begin
    if (a==4'b1001) begin
        a=4'b0000;
        if (b==4'b1001) begin
            b=4'b0000;
            if (c==4'b1001) begin
                c=4'b0000;
                if (d==4'b1001) begin
                    d=4'b0000;
                end else begin
                    d=d+4'b0001;
                end
            end else begin
                c=c+4'b0001;
            end
        end else begin
            b=b+4'b0001;
        end

        
    end else begin
    a=a+4'b0001;    
    end
    


 


     
    
end
endmodule

Verilog/Assignment/assg-3/decimal_counter/bcd_test.v
`timescale 1ns/1ns
`include "bcdcounter.v"

module bcd_test(
);
reg clk=0;
wire [15:0] o;
wire en;
bcdcounter uut(clk,o,en);
always begin
clk=~clk;#10;
    
end
initial begin
    $dumpfile("bcd_test.vcd");
    $dumpvars(0,bcd_test);
    #220;
    $stop;
end
    
endmodule

Verilog/Assignment/assg-3/decimal_counter/bcd_test.vcd
$date
	Thu Dec 21 00:54:47 2023
$end
$version
	Icarus Verilog
$end
$timescale
	1ns
$end
$scope module bcd_test $end
$var wire 1 ! en $end
$var wire 16 " o [15:0] $end
$var reg 1 # clk $end
$scope module uut $end
$var wire 1 # clk $end
$var wire 1 ! en $end
$var wire 16 $ o [15:0] $end
$var reg 4 % a [3:0] $end
$var reg 4 & b [3:0] $end
$var reg 4 ' c [3:0] $end
$var reg 4 ( d [3:0] $end
$upscope $end
$upscope $end
$enddefinitions $end
$comment Show the parameter values. $end
$dumpall
$end
#0
$dumpvars
b0 (
b0 '
b0 &
b1 %
b1 $
1#
b1 "
z!
$end
#10
0#
#20
b10 "
b10 $
b10 %
1#
#30
0#
#40
b11 "
b11 $
b11 %
1#
#50
0#
#60
b100 "
b100 $
b100 %
1#
#70
0#
#80
b101 "
b101 $
b101 %
1#
#90
0#
#100
b110 "
b110 $
b110 %
1#
#110
0#
#120
b111 "
b111 $
b111 %
1#
#130
0#
#140
b1000 "
b1000 $
b1000 %
1#
#150
0#
#160
b1001 "
b1001 $
b1001 %
1#
#170
0#
#180
b10000 "
b10000 $
b1 &
b0 %
1#
#190
0#
#200
b10001 "
b10001 $
b1 %
1#
